<?xml version="1.0" encoding="utf-8"?>
<CodeTemplates version="3.0">
  <CodeTemplate version="2.0">
    <Header>
      <_Group>UnityC#</_Group>
      <Version />
      <MimeType>text/x-csharp</MimeType>
      <Shortcut>OnFailedToConnect</Shortcut>
      <_Description />
      <TemplateType>Unknown</TemplateType>
    </Header>
    <Variables>
      <Variable name="name">
        <Default>error</Default>
      </Variable>
    </Variables>
    <Code><![CDATA[	void OnFailedToConnect (NetworkConnectionError $name$)
	{
		$selected$$end$
	}]]></Code>
  </CodeTemplate>
</CodeTemplates>